setup.cfg
setup.py
django_light_enums/__init__.py
django_light_enums/db.py
django_light_enums/enum.py
django_light_enums/models.py
django_light_enums.egg-info/PKG-INFO
django_light_enums.egg-info/SOURCES.txt
django_light_enums.egg-info/dependency_links.txt
django_light_enums.egg-info/requires.txt
django_light_enums.egg-info/top_level.txt
tests/__init__.py
tests/models.py
tests/settings.py
tests/test.py
tests/urls.py