Metadata-Version: 1.1
Name: django-light-enums
Version: 0.1.6
Summary: django-light-enums is a ligthweigth implementation of enums for Django.
Home-page: https://github.com/makingspace/django-light-enums
Author: MakeSpace Labs, Inc.
Author-email: dhites@makespace.com
License: Revised BSD
Platform: UNKNOWN
Classifier: Framework :: Django
Classifier: Intended Audience :: Developers
Classifier: License :: OSI Approved :: BSD License
Classifier: Operating System :: OS Independent
Classifier: Programming Language :: Python
Classifier: Topic :: Database
